eam_report_helper/__init__.py
eam_report_helper/report_helper.py
eam_report_helper/common/helpers.py
eam_report_helper/common/report_emp_questions.py
eam_report_helper/common/report_helper_forms.py
eam_report_helper/common/report_newly_added_vendors.py
eam_report_helper/common/report_operator_tickets.py
eam_report_helper/common/report_safety_tickets.py
eam_report_helper/common/report_vendor_deficiencies.py
eam_report_helper/common/report_vendor_documents.py
eam_report_helper-0.2.8.dist-info/METADATA
eam_report_helper-0.2.8.dist-info/WHEEL
eam_report_helper-0.2.8.dist-info/licenses/LICENSE
eam_report_helper-0.2.8.dist-info/RECORD
