Metadata-Version: 2.4
Name: eam_report_helper
Version: 0.2.8
Summary: A package that returns formatted data for reports
Author-email: Dave Gunn <daveg@8amsolutions.com>
License-File: LICENSE
Classifier: License :: OSI Approved :: MIT License
Classifier: Operating System :: OS Independent
Classifier: Programming Language :: Python :: 3
Requires-Python: >=3.8
